krtech/threads_runner.py
krtech/configuration.py
krtech/utils.py
krtech/decorators.py
krtech/steps/db_steps.py
krtech/steps/user_steps.py
krtech/steps/http_steps.py
krtech/elements/calendar.py
krtech/elements/textarea.py
krtech/elements/select.py
krtech/elements/base_element.py
krtech/elements/table.py
krtech/elements/link.py
krtech/elements/checkbox.py
krtech/elements/list.py
krtech/elements/input.py
krtech/pages/base_page.py
pytest_krtech_common-0.1.35.dist-info/WHEEL
pytest_krtech_common-0.1.35.dist-info/RECORD
pytest_krtech_common-0.1.35.dist-info/metadata.json
pytest_krtech_common-0.1.35.dist-info/METADATA
pytest_krtech_common-0.1.35.dist-info/DESCRIPTION.rst
pytest_krtech_common-0.1.35.dist-info/top_level.txt
