Metadata-Version: 2.0
Name: pytest-krtech-common
Version: 0.1.35
Summary: pytest krtech common library
Home-page: UNKNOWN
Author: Maksim Filippov
Author-email: m.filippov@krtech.ru
License: MIT
Platform: UNKNOWN
Classifier: Development Status :: 4 - Beta
Classifier: License :: OSI Approved :: MIT License
Classifier: Programming Language :: Python :: 3.4
Classifier: Environment :: Plugins
Classifier: Topic :: Software Development :: Testing
Requires-Dist: pytest
Requires-Dist: selenium
Requires-Dist: pyhamcrest
Requires-Dist: pytest-allure-adaptor
Requires-Dist: sqlalchemy
Requires-Dist: mysqlclient
Requires-Dist: requests
